Metadata-Version: 1.0
Name: phdaysdefc
Version: 10000.1
Summary: This package will be replaced by pip due to dependancy confusion
Home-page: UNKNOWN
Author: nguna
Author-email: nishaanth@appknox.com
License: UNKNOWN
Platform: UNKNOWN
